pte_xdf/__init__.py
pte_xdf/xdf.py
pte_xdf-0.1.0.dist-info/LICENSE
pte_xdf-0.1.0.dist-info/WHEEL
pte_xdf-0.1.0.dist-info/METADATA
pte_xdf-0.1.0.dist-info/RECORD
