Metadata-Version: 2.1
Name: pte-xdf
Version: 0.1.0
Summary: A package for loading XDF files recorded with TMSi amplifiers.
Keywords: xdf,tmsi,eeg,ieeg
Author: Richard M. Köhler
Maintainer: Richard M. Köhler
Requires-Python: >=3.10
Classifier: Development Status :: 2 - Pre-Alpha
Classifier: License :: OSI Approved :: Apache Software License
Classifier: Programming Language :: Python
Classifier: Topic :: Software Development :: Libraries :: Python Modules
Requires-Dist: mne
Requires-Dist: numpy
Requires-Dist: pyxdf
Requires-Dist: black ; extra == "dev"
Requires-Dist: isort ; extra == "dev"
Requires-Dist: mypy ; extra == "dev"
Requires-Dist: pylint ; extra == "dev"
Requires-Dist: pytest ; extra == "dev"
Requires-Dist: pytest-cov ; extra == "dev"
Requires-Dist: tox ; extra == "dev"
Requires-Dist: mkdocs ; extra == "doc"
Requires-Dist: mkdocs-autorefs ; extra == "doc"
Requires-Dist: mkdocs-material ; extra == "doc"
Requires-Dist: mkdocstrings[python] ; extra == "doc"
Requires-Dist: pte-xdf[dev,doc,release] ; extra == "full"
Requires-Dist: pip-tools ; extra == "release"
Project-URL: bugtracker, https://github.com/richardkoehler/pte-xdf/issues
Project-URL: changelog, https://github.com/richardkoehler/pte-xdf/blob/main/docs/CHANGELOG.md
Project-URL: repository, https://github.com/richardkoehler/pte-xdf
Provides-Extra: dev
Provides-Extra: doc
Provides-Extra: full
Provides-Extra: release
